{
  "medicamentos": [
    {
      "medicamento": 1,
      "pontos": [
        {
          "ponto": 1,
          "x": 242.9171,
          "y": -3.0702,
          "z": 151.2782,
          "r": -0.7241,
          "movimento": "movj",
          "suctionCup": "off"
        },
        {
          "ponto": 2,
          "x": 259.2058,
          "y": -155.618,
          "z": 138.9601,
          "r": -30.9791,
          "movimento": "movj",
          "suctionCup": "off"
        },
        {
          "ponto": 3,
          "x": 242.6397,
          "y": -145.5158,
          "z": 51.3692,
          "r": -30.9519,
          "movimento": "movl",
          "suctionCup": "off"
        },
        {
          "ponto": 4,
          "x": 245.0075,
          "y": -147.0339,
          "z": 19.1576,
          "r": -30.9688,
          "movimento": "movl",
          "suctionCup": "on"
        },
        {
          "ponto": 5,
          "x": 252.059,
          "y": -138.5856,
          "z": 133.2815,
          "r": -28.8026,
          "movimento": "movl",
          "suctionCup": "on"
        },
        {
          "ponto": 6,
          "x": -68.2342,
          "y": -252.4319,
          "z": 139.5452,
          "r": -105.126,
          "movimento": "movj",
          "suctionCup": "on"
        },
        {
          "ponto": 7,
          "x": -93.0062,
          "y": -327.6319,
          "z": 100.1649,
          "r": -105.8479,
          "movimento": "movl",
          "suctionCup": "on"
        },
        {
          "ponto": 8,
          "x": -101.1502,
          "y": -311.0937,
          "z": -3.8156,
          "r": -108.0116,
          "movimento": "movj",
          "suctionCup": "on"
        },
        {
          "ponto": 9,
          "x": -108.2273,
          "y": -319.1638,
          "z": -25.5562,
          "r": -108.7316,
          "movimento": "movl",
          "suctionCup": "off"
        },
        {
          "ponto": 10,
          "x": -95.5803,
          "y": -307.4564,
          "z": 117.7957,
          "r": -107.2691,
          "movimento": "movl",
          "suctionCup": "off"
        },
        {
          "ponto": 11,
          "x": -48.3327,
          "y": -237.3098,
          "z": 155.6866,
          "r": -101.5119,
          "movimento": "movj",
          "suctionCup": "off"
        }
      ]
    },
    {
      "medicamento": 2,
      "pontos": [
        {
          "ponto": 1,
          "x": 241.4546,
          "y": 3.0644,
          "z": 170.9226,
          "r": 0.7271,
          "movimento": "movj",
          "suctionCup": "off"
        },
        {
          "ponto": 2,
          "x": 257.4303,
          "y": -80.2502,
          "z": 149.1581,
          "r": -17.3141,
          "movimento": "movj",
          "suctionCup": "off"
        },
        {
          "ponto": 3,
          "x": 253.4617,
          "y": -71.9998,
          "z": 44.2543,
          "r": -15.858,
          "movimento": "movl",
          "suctionCup": "off"
        },
        {
          "ponto": 4,
          "x": 250.8229,
          "y": -74.7884,
          "z": 17.5412,
          "r": -16.6031,
          "movimento": "movl",
          "suctionCup": "on"
        },
        {
          "ponto": 5,
          "x": 252.4085,
          "y": -68.3343,
          "z": 139.1531,
          "r": -15.1485,
          "movimento": "movl",
          "suctionCup": "on"
        },
        {
          "ponto": 6,
          "x": -82.3987,
          "y": -224.0239,
          "z": 141.1509,
          "r": -110.1941,
          "movimento": "movj",
          "suctionCup": "on"
        },
        {
          "ponto": 7,
          "x": -90.1212,
          "y": -254.6694,
          "z": 123.244,
          "r": -109.4876,
          "movimento": "movj",
          "suctionCup": "on"
        },
        {
          "ponto": 8,
          "x": -106.5637,
          "y": -259.1319,
          "z": 5.9154,
          "r": -112.3541,
          "movimento": "movl",
          "suctionCup": "on"
        },
        {
          "ponto": 9,
          "x": -109.0249,
          "y": -265.1759,
          "z": -30.9942,
          "r": -112.3496,
          "movimento": "movl",
          "suctionCup": "off"
        },
        {
          "ponto": 10,
          "x": -103.1875,
          "y": -259.9458,
          "z": 136.0332,
          "r": -111.651,
          "movimento": "movj",
          "suctionCup": "off"
        }
      ]
    },
    {
      "medicamento": 3,
      "pontos": [
        {
          "ponto": 1,
          "x": 223.3705,
          "y": 2.6595,
          "z": 158.8508,
          "r": 0.6821,
          "movimento": "movj",
          "suctionCup": "off"
        },
        {
          "ponto": 2,
          "x": 261.1666,
          "y": 3.1266,
          "z": 132.2927,
          "r": 0.6859,
          "movimento": "movj",
          "suctionCup": "off"
        },
        {
          "ponto": 3,
          "x": 249.7307,
          "y": -0.1487,
          "z": 49.2467,
          "r": -0.0341,
          "movimento": "movj",
          "suctionCup": "off"
        },
        {
          "ponto": 4,
          "x": 255.3126,
          "y": -0.1771,
          "z": 20.9612,
          "r": -0.0397,
          "movimento": "movj",
          "suctionCup": "on"
        },
        {
          "ponto": 5,
          "x": 258.3978,
          "y": -0.1792,
          "z": 143.5855,
          "r": -0.0397,
          "movimento": "movj",
          "suctionCup": "on"
        },
        {
          "ponto": 6,
          "x": 13.2803,
          "y": -273.2101,
          "z": 141.4234,
          "r": -87.2171,
          "movimento": "movj",
          "suctionCup": "on"
        },
        {
          "ponto": 7,
          "x": -29.7631,
          "y": -331.3598,
          "z": 94.6734,
          "r": -95.1326,
          "movimento": "movj",
          "suctionCup": "on"
        },
        {
          "ponto": 8,
          "x": -29.2311,
          "y": -325.7227,
          "z": -9.2569,
          "r": -95.1281,
          "movimento": "movj",
          "suctionCup": "on"
        },
        {
          "ponto": 9,
          "x": -29.4616,
          "y": -328.0032,
          "z": -33.2036,
          "r": -95.1326,
          "movimento": "movj",
          "suctionCup": "off"
        },
        {
          "ponto": 10,
          "x": -29.6693,
          "y": -330.8966,
          "z": 64.3731,
          "r": -95.1236,
          "movimento": "movj",
          "suctionCup": "off"
        },
        {
          "ponto": 11,
          "x": -6.093,
          "y": -227.7281,
          "z": 155.2563,
          "r": -91.5326,
          "movimento": "movj",
          "suctionCup": "off"
        }
      ]
    },
    {
      "medicamento": 4,
      "pontos": [
        {
          "ponto": 1,
          "x": 242.4661,
          "y": -12.462,
          "z": 158.9673,
          "r": -2.9422,
          "movimento": "movj",
          "suctionCup": "off"
        },
        {
          "ponto": 1,
          "x": 256.7684,
          "y": 69.192,
          "z": 157.8803,
          "r": 15.0814,
          "movimento": "movj",
          "suctionCup": "off"
        },
        {
          "ponto": 2,
          "x": 260.5082,
          "y": 73.7011,
          "z": 41.482,
          "r": 15.7969,
          "movimento": "movj",
          "suctionCup": "off"
        },
        {
          "ponto": 2,
          "x": 248.213,
          "y": 73.593,
          "z": 19.4882,
          "r": 16.5146,
          "movimento": "movj",
          "suctionCup": "on"
        },
        {
          "ponto": 2,
          "x": 257.7855,
          "y": 65.9813,
          "z": 153.8425,
          "r": 14.3569,
          "movimento": "movj",
          "suctionCup": "on"
        },
        {
          "ponto": 1,
          "x": -3.1022,
          "y": -235.6829,
          "z": 155.9082,
          "r": -90.7541,
          "movimento": "movj",
          "suctionCup": "on"
        },
        {
          "ponto": 1,
          "x": -35.5011,
          "y": -278.3681,
          "z": 85.9457,
          "r": -97.2678,
          "movimento": "movj",
          "suctionCup": "on"
        },
        {
          "ponto": 2,
          "x": -30.3419,
          "y": -265.2633,
          "z": -5.9251,
          "r": -96.5253,
          "movimento": "movj",
          "suctionCup": "on"
        },
        {
          "ponto": 2,
          "x": -31.0345,
          "y": -271.7901,
          "z": -31.8394,
          "r": -96.5141,
          "movimento": "movj",
          "suctionCup": "off"
        },
        {
          "ponto": 2,
          "x": -34.8152,
          "y": -273.2744,
          "z": 10.169,
          "r": -97.2604,
          "movimento": "movj",
          "suctionCup": "off"
        },
        {
          "ponto": 1,
          "x": -24.5642,
          "y": -240.9468,
          "z": 148.6979,
          "r": -95.8211,
          "movimento": "movj",
          "suctionCup": "off"
        }
      ]
    },
    {
      "medicamento": 5,
      "pontos": [
        {
          "ponto": 1,
          "x": 242.5288,
          "y": -2.978,
          "z": 167.075,
          "r": -0.7035,
          "movimento": "movj",
          "suctionCup": "off"
        },
        {
          "ponto": 2,
          "x": 249.2707,
          "y": 136.9974,
          "z": 157.6279,
          "r": 28.7929,
          "movimento": "movj",
          "suctionCup": "off"
        },
        {
          "ponto": 3,
          "x": 251.7976,
          "y": 146.8492,
          "z": 43.361,
          "r": 30.2509,
          "movimento": "movj",
          "suctionCup": "off"
        },
        {
          "ponto": 4,
          "x": 259.3742,
          "y": 146.9539,
          "z": 15.6511,
          "r": 29.5346,
          "movimento": "movj",
          "suctionCup": "on"
        },
        {
          "ponto": 5,
          "x": 255.8397,
          "y": 140.6077,
          "z": 147.5765,
          "r": 28.7929,
          "movimento": "movj",
          "suctionCup": "on"
        },
        {
          "ponto": 6,
          "x": 97.4393,
          "y": -255.8179,
          "z": 156.4059,
          "r": -69.1485,
          "movimento": "movj",
          "suctionCup": "on"
        },
        {
          "ponto": 7,
          "x": 64.1482,
          "y": -297.6808,
          "z": 61.4695,
          "r": -77.8391,
          "movimento": "movj",
          "suctionCup": "on"
        },
        {
          "ponto": 8,
          "x": 45.9817,
          "y": -304.233,
          "z": 17.7106,
          "r": -81.4054,
          "movimento": "movj",
          "suctionCup": "on"
        },
        {
          "ponto": 9,
          "x": 48.5697,
          "y": -296.8528,
          "z": -29.9873,
          "r": -80.7079,
          "movimento": "movj",
          "suctionCup": "off"
        },
        {
          "ponto": 10,
          "x": 55.3356,
          "y": -292.1465,
          "z": 6.8281,
          "r": -79.2746,
          "movimento": "movj",
          "suctionCup": "off"
        },
        {
          "ponto": 11,
          "x": 59.9016,
          "y": -234.007,
          "z": 137.5002,
          "r": -75.6416,
          "movimento": "movj",
          "suctionCup": "off"
        }
      ]
    }
  ]
}